CHANGES.rst
CONTRIBUTORS.rst
LICENSE.GPL
LICENSE.rst
MANIFEST.in
README.rst
requirements.txt
setup.cfg
setup.py
docs/index.rst
src/collective/__init__.py
src/collective.smartappbanner.egg-info/PKG-INFO
src/collective.smartappbanner.egg-info/SOURCES.txt
src/collective.smartappbanner.egg-info/dependency_links.txt
src/collective.smartappbanner.egg-info/entry_points.txt
src/collective.smartappbanner.egg-info/namespace_packages.txt
src/collective.smartappbanner.egg-info/not-zip-safe
src/collective.smartappbanner.egg-info/requires.txt
src/collective.smartappbanner.egg-info/top_level.txt
src/collective/smartappbanner/__init__.py
src/collective/smartappbanner/configure.zcml
src/collective/smartappbanner/interfaces.py
src/collective/smartappbanner/profiles.zcml
src/collective/smartappbanner/setuphandlers.py
src/collective/smartappbanner/testing.py
src/collective/smartappbanner/browser/__init__.py
src/collective/smartappbanner/browser/configure.zcml
src/collective/smartappbanner/browser/interfaces.py
src/collective/smartappbanner/browser/settings.py
src/collective/smartappbanner/browser/smartappbanner.pt
src/collective/smartappbanner/browser/viewlets.py
src/collective/smartappbanner/browser/overrides/.gitkeep
src/collective/smartappbanner/browser/static/.gitkeep
src/collective/smartappbanner/browser/static/smart-app-banner.css
src/collective/smartappbanner/browser/static/smart-app-banner.js
src/collective/smartappbanner/locales/collective.smartappbanner.pot
src/collective/smartappbanner/locales/update.sh
src/collective/smartappbanner/locales/nl/LC_MESSAGES/collective.smartappbanner.mo
src/collective/smartappbanner/locales/nl/LC_MESSAGES/collective.smartappbanner.po
src/collective/smartappbanner/profiles/default/browserlayer.xml
src/collective/smartappbanner/profiles/default/controlpanel.xml
src/collective/smartappbanner/profiles/default/cssregistry.xml
src/collective/smartappbanner/profiles/default/jsregistry.xml
src/collective/smartappbanner/profiles/default/metadata.xml
src/collective/smartappbanner/profiles/default/registry.xml
src/collective/smartappbanner/profiles/uninstall/browserlayer.xml
src/collective/smartappbanner/profiles/uninstall/controlpanel.xml
src/collective/smartappbanner/profiles/uninstall/cssregistry.xml
src/collective/smartappbanner/profiles/uninstall/jsregistry.xml
src/collective/smartappbanner/profiles/uninstall/registry.xml
src/collective/smartappbanner/tests/__init__.py
