Metadata-Version: 1.1
Name: collective.smartappbanner
Version: 1.0.1
Summary: Smart app banners on Plone for iOS, Android, and Windows.
Home-page: https://pypi.python.org/pypi/collective.smartappbanner
Author: Zest Software
Author-email: info@zestsoftware.nl
License: GPL version 2
Keywords: Python Plone
Platform: UNKNOWN
Classifier: Environment :: Web Environment
Classifier: Framework :: Plone
Classifier: Framework :: Plone :: 4.3
Classifier: Programming Language :: Python
Classifier: Programming Language :: Python :: 2.7
Classifier: Operating System :: OS Independent
Classifier: License :: OSI Approved :: GNU General Public License v2 (GPLv2)
